.DS_Store
shane/__init__.py
shane/__version__.py
shane/_api.py
shane/_container.py
shane/_ffmpeg.py
shane/_new_variables.py
shane/_streams.py
shane/_utils.py
shane/frame_sizes.py
shane/muxers.py
shane-18.8b2.dist-info/METADATA
shane-18.8b2.dist-info/RECORD
shane-18.8b2.dist-info/WHEEL
shane-18.8b2.dist-info/top_level.txt
