Metadata-Version: 2.1
Name: shane
Version: 18.8b2
Summary: A simple way to manage video files.
Home-page: https://github.com/dmkskn/shane
Author: Dima Koskin
Author-email: dmksknn@gmail.com
License: MIT
Keywords: video metadata converting muxing ffmpeg
Platform: UNKNOWN
Classifier: Development Status :: 4 - Beta
Classifier: License :: OSI Approved :: MIT License
Classifier: Intended Audience :: Developers
Classifier: Programming Language :: Python
Classifier: Programming Language :: Python :: 3
Classifier: Programming Language :: Python :: 3.6
Classifier: Programming Language :: Python :: 3 :: Only
Classifier: Topic :: Multimedia
Classifier: Topic :: Multimedia :: Video
Classifier: Topic :: Multimedia :: Video :: Conversion
Requires-Python: >=3.6
